{
    "window": {
        "icon": "assets/icon.png",
        "title": "Le jeu de la vie",
        "width": 1920,
        "height": 1080,
        "resizable": false,
        "fullscreen": true,
        "show": true,
        "center": true
    },
    "inputsmouse": {
        "left": "BUTTON_LEFT",
        "middle": "BUTTON_MIDDLE",
        "right": "BUTTON_RIGHT",
        "scrollup": "BUTTON_WHEELUP",
        "scrolldown": "BUTTON_WHEELDOWN"
    },
    "inputskeyboard": {
        "backspace": "K_BACKSPACE",
        "tab": "K_TAB",
        "clear": "K_CLEAR",
        "enter": "K_RETURN",
        "pause": "K_PAUSE",
        "escape": "K_ESCAPE",
        "space": "K_SPACE",
        "exclamation": "K_EXCLAIM",
        "doublequote": "K_QUOTEDBL",
        "hash": "K_HASH",
        "dollar": "K_DOLLAR",
        "ampersand": "K_AMPERSAND",
        "quote": "K_QUOTE",
        "leftparen": "K_LEFTPAREN",
        "rightparen": "K_RIGHTPAREN",
        "asterisk": "K_ASTERISK",
        "plus": "K_PLUS",
        "comma": "K_COMMA",
        "minus": "K_MINUS",
        "period": "K_PERIOD",
        "slash": "K_SLASH",
        "0": "K_0",
        "1": "K_1",
        "2": "K_2",
        "3": "K_3",
        "4": "K_4",
        "5": "K_5",
        "6": "K_6",
        "7": "K_7",
        "8": "K_8",
        "9": "K_9",
        "colon": "K_COLON",
        "semicolon": "K_SEMICOLON",
        "less": "K_LESS",
        "equals": "K_EQUALS",
        "greater": "K_GREATER",
        "question": "K_QUESTION",
        "at": "K_AT",
        "leftbracket": "K_LEFTBRACKET",
        "backslash": "K_BACKSLASH",
        "rightbracket": "K_RIGHTBRACKET",
        "caret": "K_CARET",
        "underscore": "K_UNDERSCORE",
        "backquote": "K_BACKQUOTE",
        "a": "K_a",
        "b": "K_b",
        "c": "K_c",
        "d": "K_d",
        "e": "K_e",
        "f": "K_f",
        "g": "K_g",
        "h": "K_h",
        "i": "K_i",
        "j": "K_j",
        "k": "K_k",
        "l": "K_l",
        "m": "K_m",
        "n": "K_n",
        "o": "K_o",
        "p": "K_p",
        "q": "K_q",
        "r": "K_r",
        "s": "K_s",
        "t": "K_t",
        "u": "K_u",
        "v": "K_v",
        "w": "K_w",
        "x": "K_x",
        "y": "K_y",
        "z": "K_z",
        "delete": "K_DELETE",
        "kp0": "K_KP0",
        "kp1": "K_KP1",
        "kp2": "K_KP2",
        "kp3": "K_KP3",
        "kp4": "K_KP4",
        "kp5": "K_KP5",
        "kp6": "K_KP6",
        "kp7": "K_KP7",
        "kp8": "K_KP8",
        "kp9": "K_KP9",
        "kp_period": "K_KP_PERIOD",
        "kp_divide": "K_KP_DIVIDE",
        "kp_multiply": "K_KP_MULTIPLY",
        "kp_minus": "K_KP_MINUS",
        "kp_plus": "K_KP_PLUS",
        "kp_enter": "K_KP_ENTER",
        "kp_equals": "K_KP_EQUALS",
        "kup": "K_UP",
        "kdown": "K_DOWN",
        "kright": "K_RIGHT",
        "kleft": "K_LEFT",
        "insert": "K_INSERT",
        "home": "K_HOME",
        "end": "K_END",
        "pageup": "K_PAGEUP",
        "pagedown": "K_PAGEDOWN",
        "f1": "K_F1",
        "f2": "K_F2",
        "f3": "K_F3",
        "f4": "K_F4",
        "f5": "K_F5",
        "f6": "K_F6",
        "f7": "K_F7",
        "f8": "K_F8",
        "f9": "K_F9",
        "f10": "K_F10",
        "f11": "K_F11",
        "f12": "K_F12",
        "numlock": "K_NUMLOCK",
        "capslock": "K_CAPSLOCK",
        "scrolllock": "K_SCROLLOCK",
        "rshift": "K_RSHIFT",
        "lshift": "K_LSHIFT",
        "rctrl": "K_RCTRL",
        "lctrl": "K_LCTRL",
        "ralt": "K_RALT",
        "lalt": "K_LALT",
        "rsuper": "K_RMETA",
        "lsuper": "K_LMETA",
        "mode": "K_MODE",
        "help": "K_HELP",
        "print": "K_PRINT",
        "sysreq": "K_SYSREQ",
        "break": "K_BREAK",
        "menu": "K_MENU",
        "power": "K_POWER",
        "euro": "K_EURO"
    }
}
